packagit-0.2102.16.data/scripts/packagit
packagit_/__init__.py
packagit_/packagit.py
packagit-0.2102.16.dist-info/LICENSE
packagit-0.2102.16.dist-info/METADATA
packagit-0.2102.16.dist-info/WHEEL
packagit-0.2102.16.dist-info/top_level.txt
packagit-0.2102.16.dist-info/RECORD
