Metadata-Version: 2.1
Name: packagit
Version: 0.2102.16
Summary: Increment version, create and push tag for release
Home-page: https://github.com/davips/packagit
Author: Davi Pereira-Santos
Author-email: dpsabc@gmail.com
License: GPL3
Download-URL: https://github.com/davips/packagit/releases
Platform: UNKNOWN
Classifier: Intended Audience :: Science/Research
Classifier: License :: OSI Approved :: GNU General Public License v3 (GPLv3)
Classifier: Natural Language :: English
Classifier: Programming Language :: Python
Classifier: Topic :: Scientific/Engineering
Classifier: Programming Language :: Python :: 3.8
Requires-Dist: gitpython
